browsefn/__init__.py
browsefn/adapters/fastapi.py
browsefn/core/browse_fn.py
browsefn/core/cache_manager.py
browsefn/core/provider_manager.py
browsefn/core/rate_limiter.py
browsefn/core/types.py
browsefn/geo/geocoder.py
browsefn/geo/providers/__init__.py
browsefn/geo/providers/google_maps.py
browsefn/geo/providers/mapbox.py
browsefn/geo/providers/nominatim.py
browsefn/http/router.py
browsefn/images/browser.py
browsefn/images/providers/__init__.py
browsefn/images/providers/pexels.py
browsefn/images/providers/pixabay.py
browsefn/images/providers/unsplash.py
browsefn/middleware/__init__.py
browsefn/middleware/logging.py
browsefn/middleware/metrics.py
browsefn/middleware/retry.py
browsefn/utils/__init__.py
browsefn/utils/html_utils.py
browsefn/utils/url_utils.py
browsefn/utils/validation.py
browsefn/web/scraper.py
browsefn/web/providers/bs4.py
browsefn-0.0.1.dist-info/METADATA
browsefn-0.0.1.dist-info/WHEEL
browsefn-0.0.1.dist-info/RECORD
