Metadata-Version: 2.4
Name: browsefn
Version: 0.0.1
Summary: Comprehensive self-hosted web browsing and data extraction platform for developers
Author: 21n
License-Expression: Apache-2.0
Keywords: crawling,geolocation,images,sdk,web-scraping
Classifier: Development Status :: 3 - Alpha
Classifier: Intended Audience :: Developers
Classifier: License :: OSI Approved :: Apache Software License
Classifier: Programming Language :: Python :: 3
Classifier: Programming Language :: Python :: 3.8
Classifier: Programming Language :: Python :: 3.9
Classifier: Programming Language :: Python :: 3.10
Classifier: Programming Language :: Python :: 3.11
Classifier: Programming Language :: Python :: 3.12
Requires-Python: >=3.8
Requires-Dist: beautifulsoup4>=4.12.0
Requires-Dist: html2text>=2020.1.16
Requires-Dist: httpx>=0.27.0
Requires-Dist: pydantic>=2.0.0
Requires-Dist: sfns>=0.1.0
Requires-Dist: tenacity>=8.2.0
Requires-Dist: typing-extensions>=4.0.0
Provides-Extra: fastapi
Requires-Dist: fastapi>=0.100.0; extra == 'fastapi'
Requires-Dist: superfunctions-fastapi>=0.1.0; extra == 'fastapi'
Requires-Dist: uvicorn>=0.20.0; extra == 'fastapi'
Provides-Extra: playwright
Requires-Dist: playwright>=1.40.0; extra == 'playwright'
Provides-Extra: test
Requires-Dist: mypy>=1.0.0; extra == 'test'
Requires-Dist: pytest-asyncio>=0.23.0; extra == 'test'
Requires-Dist: pytest-cov>=4.1.0; extra == 'test'
Requires-Dist: pytest>=7.0.0; extra == 'test'
